betterplaysound/__init__.py
betterplaysound/betterplaysound.py
betterplaysound-1.0.dist-info/METADATA
betterplaysound-1.0.dist-info/WHEEL
betterplaysound-1.0.dist-info/entry_points.txt
betterplaysound-1.0.dist-info/top_level.txt
betterplaysound-1.0.dist-info/RECORD
